canadapost/__init__.py
canadapost/exceptions.py
canadapost/https.py
canadapost/api/base.py
canadapost/api/contract.py
canadapost/api/non_contract.py
canadapost/api/rating.py
canadapost/client/base.py
canadapost/client/sync.py
canadapost/client/synca.py
canadapost/objects/address_details.py
canadapost/objects/adjustment.py
canadapost/objects/adjustment_qualifier.py
canadapost/objects/adjustments.py
canadapost/objects/base.py
canadapost/objects/cc_receipt_details.py
canadapost/objects/cod_remittance.py
canadapost/objects/customs.py
canadapost/objects/delivery_spec.py
canadapost/objects/destination.py
canadapost/objects/dimensional_restrictions.py
canadapost/objects/dimensions.py
canadapost/objects/domestic.py
canadapost/objects/item.py
canadapost/objects/mailing_scenario.py
canadapost/objects/non_contract_shipment.py
canadapost/objects/non_contract_shipment_details.py
canadapost/objects/non_contract_shipment_info.py
canadapost/objects/non_contract_shipment_receipt.py
canadapost/objects/non_contract_shipment_refund_request.py
canadapost/objects/non_contract_shipment_refund_request_info.py
canadapost/objects/non_contract_shipments.py
canadapost/objects/notification.py
canadapost/objects/option.py
canadapost/objects/options.py
canadapost/objects/parcel_characteristics.py
canadapost/objects/preferences.py
canadapost/objects/price_details.py
canadapost/objects/price_quote.py
canadapost/objects/price_quotes.py
canadapost/objects/priced_option.py
canadapost/objects/qualifier.py
canadapost/objects/recipient.py
canadapost/objects/references.py
canadapost/objects/restrictions.py
canadapost/objects/sender.py
canadapost/objects/service.py
canadapost/objects/service_standard.py
canadapost/objects/services.py
canadapost/objects/settlement_info.py
canadapost/objects/taxes.py
canadapost-0.0.1.dist-info/LICENSE
canadapost-0.0.1.dist-info/METADATA
canadapost-0.0.1.dist-info/WHEEL
canadapost-0.0.1.dist-info/top_level.txt
canadapost-0.0.1.dist-info/RECORD
